seqranker/__init__.py
seqranker/__main__.py
seqranker-0.1.4.dist-info/LICENSE
seqranker-0.1.4.dist-info/METADATA
seqranker-0.1.4.dist-info/WHEEL
seqranker-0.1.4.dist-info/entry_points.txt
seqranker-0.1.4.dist-info/top_level.txt
seqranker-0.1.4.dist-info/RECORD
