Metadata-Version: 2.1
Name: seqranker
Version: 0.1.4
Summary: dbDNA - A phylogeny- and expert identifier-driven grading system for reliable taxonomic annotation of (meta)barcoding data
Home-page: https://github.com/TillMacher/dbdna
Author: Till-Hendrik Macher
Author-email: macher@uni-trier.de
License: MIT
Classifier: Programming Language :: Python :: 3
Classifier: License :: OSI Approved :: MIT License
Classifier: Operating System :: OS Independent
Requires-Python: >=3.10
License-File: LICENSE
Requires-Dist: Bio>=1.7.1
Requires-Dist: biopython>=1.84
Requires-Dist: ete3>=3.1.3
Requires-Dist: joblib>=1.4.2
Requires-Dist: numpy>=2.2.4
Requires-Dist: pandas>=2.2.3
Requires-Dist: playwright>=1.51.0
Requires-Dist: plotly>=5.9.0
Requires-Dist: PyPDF2>=3.0.1
Requires-Dist: Requests>=2.32.3
Requires-Dist: requests-html>=0.10.0
Requires-Dist: tqdm>=4.66.4
Requires-Dist: xmltodict>=0.13.0
Requires-Dist: lxml-html-clean>=0.4.1
Requires-Dist: openpyxl>=3.1.5
Requires-Dist: pyarrow>=19.0.1
Requires-Dist: fastparquet>=2024.11.0
Requires-Dist: kaleido>=0.2.1
